sedate/__init__.py
sedate/py.typed
sedate/types.py
sedate-1.2.0.dist-info/METADATA
sedate-1.2.0.dist-info/WHEEL
sedate-1.2.0.dist-info/top_level.txt
sedate-1.2.0.dist-info/RECORD
