Metadata-Version: 2.2
Name: sedate
Version: 1.2.0
Summary: Date/time helper functions used by various Seantis packages.
Home-page: http://github.com/seantis/sedate
Author: Seantis GmbH
Author-email: info@seantis.ch
License: GPLv2
Project-URL: Bug Tracker, http://github.com/seantis/sedate/issues
Classifier: Development Status :: 5 - Production/Stable
Classifier: License :: OSI Approved
Classifier: License :: OSI Approved :: GNU General Public License v2 (GPLv2)
Classifier: Programming Language :: Python
Classifier: Programming Language :: Python :: 3
Classifier: Programming Language :: Python :: 3.9
Classifier: Programming Language :: Python :: 3.10
Classifier: Programming Language :: Python :: 3.11
Classifier: Programming Language :: Python :: 3.12
Classifier: Programming Language :: Python :: 3.13
Classifier: Programming Language :: Python :: Implementation :: CPython
Classifier: Intended Audience :: Developers
Classifier: Topic :: Software Development :: Libraries :: Python Modules
Requires-Python: >=3.9
Requires-Dist: pytz
Provides-Extra: dev
Requires-Dist: bump-my-version; extra == "dev"
Requires-Dist: flake8; extra == "dev"
Requires-Dist: flake8-type-checking; extra == "dev"
Requires-Dist: mypy; extra == "dev"
Requires-Dist: pre-commit; extra == "dev"
Requires-Dist: pre-commit-uv; extra == "dev"
Requires-Dist: ruff; extra == "dev"
Requires-Dist: tox; extra == "dev"
Requires-Dist: tox-uv; extra == "dev"
Requires-Dist: types-pytz; extra == "dev"
Requires-Dist: uv; extra == "dev"
